{
  "/_not-found/page": "app/_not-found/page.js",
  "/accessibility/page": "app/accessibility/page.js",
  "/admin/analytics/page": "app/admin/analytics/page.js",
  "/about/page": "app/about/page.js",
  "/admin/audit-logs/page": "app/admin/audit-logs/page.js",
  "/admin/content/page": "app/admin/content/page.js",
  "/admin/compliance/page": "app/admin/compliance/page.js",
  "/admin/events/page": "app/admin/events/page.js",
  "/admin/groups/page": "app/admin/groups/page.js",
  "/admin/jobs/page": "app/admin/jobs/page.js",
  "/admin/settings/page": "app/admin/settings/page.js",
  "/admin/page": "app/admin/page.js",
  "/admin/subscriptions/page": "app/admin/subscriptions/page.js",
  "/careers/page": "app/careers/page.js",
  "/admin/users/page": "app/admin/users/page.js",
  "/community/page": "app/community/page.js",
  "/blog/page": "app/blog/page.js",
  "/contact-sales/page": "app/contact-sales/page.js",
  "/cookies/page": "app/cookies/page.js",
  "/courses/page": "app/courses/page.js",
  "/employer/organizations/[orgId]/analytics/page": "app/employer/organizations/[orgId]/analytics/page.js",
  "/employer/organizations/[orgId]/applications/page": "app/employer/organizations/[orgId]/applications/page.js",
  "/employer/organizations/[orgId]/education/applications/page": "app/employer/organizations/[orgId]/education/applications/page.js",
  "/employer/organizations/[orgId]/education/outcomes/page": "app/employer/organizations/[orgId]/education/outcomes/page.js",
  "/employer/organizations/[orgId]/jobs/new/page": "app/employer/organizations/[orgId]/jobs/new/page.js",
  "/employer/organizations/[orgId]/jobs/page": "app/employer/organizations/[orgId]/jobs/page.js",
  "/employer/organizations/[orgId]/page": "app/employer/organizations/[orgId]/page.js",
  "/employer/organizations/[orgId]/team/page": "app/employer/organizations/[orgId]/team/page.js",
  "/employer/organizations/new/page": "app/employer/organizations/new/page.js",
  "/employer/page": "app/employer/page.js",
  "/forgot-password/page": "app/forgot-password/page.js",
  "/help/appeal/page": "app/help/appeal/page.js",
  "/help/transparency-report/page": "app/help/transparency-report/page.js",
  "/jobs/page": "app/jobs/page.js",
  "/jobs/[id]/page": "app/jobs/[id]/page.js",
  "/login/page": "app/login/page.js",
  "/maintenance/page": "app/maintenance/page.js",
  "/mentor-agreement/page": "app/mentor-agreement/page.js",
  "/mentors/page": "app/mentors/page.js",
  "/onboarding/page": "app/onboarding/page.js",
  "/page": "app/page.js",
  "/press/page": "app/press/page.js",
  "/pricing/page": "app/pricing/page.js",
  "/privacy-center/page": "app/privacy-center/page.js",
  "/privacy/page": "app/privacy/page.js",
  "/register/page": "app/register/page.js",
  "/privacy/uk/page": "app/privacy/uk/page.js",
  "/report/page": "app/report/page.js",
  "/reset-password/page": "app/reset-password/page.js",
  "/safety-center/page": "app/safety-center/page.js",
  "/terms/page": "app/terms/page.js",
  "/verify-email/page": "app/verify-email/page.js",
  "/help/community-guidelines/page": "app/help/community-guidelines/page.js",
  "/help/safety-center/page": "app/help/safety-center/page.js",
  "/dashboard/accelerator/page": "app/dashboard/accelerator/page.js",
  "/dashboard/ai/career-path/page": "app/dashboard/ai/career-path/page.js",
  "/dashboard/ai/chat/page": "app/dashboard/ai/chat/page.js",
  "/dashboard/ai/career-compass/page": "app/dashboard/ai/career-compass/page.js",
  "/dashboard/ai/content-generator/page": "app/dashboard/ai/content-generator/page.js",
  "/dashboard/ai/idea-validator/page": "app/dashboard/ai/idea-validator/page.js",
  "/dashboard/ai/creator/page": "app/dashboard/ai/creator/page.js",
  "/dashboard/ai/interview-coach/page": "app/dashboard/ai/interview-coach/page.js",
  "/dashboard/ai/opportunities/page": "app/dashboard/ai/opportunities/page.js",
  "/dashboard/ai/mentors/page": "app/dashboard/ai/mentors/page.js",
  "/dashboard/ai/page": "app/dashboard/ai/page.js",
  "/dashboard/ai/opportunity-radar/page": "app/dashboard/ai/opportunity-radar/page.js",
  "/dashboard/ai/resume-optimizer/page": "app/dashboard/ai/resume-optimizer/page.js",
  "/dashboard/ai/trust/page": "app/dashboard/ai/trust/page.js",
  "/dashboard/ai/salary/page": "app/dashboard/ai/salary/page.js",
  "/dashboard/community/page": "app/dashboard/community/page.js",
  "/dashboard/applications/page": "app/dashboard/applications/page.js",
  "/dashboard/companies/page": "app/dashboard/companies/page.js",
  "/dashboard/creator/page": "app/dashboard/creator/page.js",
  "/dashboard/events/page": "app/dashboard/events/page.js",
  "/dashboard/create-post/page": "app/dashboard/create-post/page.js",
  "/dashboard/creator-studio/page": "app/dashboard/creator-studio/page.js",
  "/dashboard/finance/health/page": "app/dashboard/finance/health/page.js",
  "/dashboard/finance/money/page": "app/dashboard/finance/money/page.js",
  "/dashboard/finance/insurance/page": "app/dashboard/finance/insurance/page.js",
  "/dashboard/finance/inventory/page": "app/dashboard/finance/inventory/page.js",
  "/dashboard/finance/accounting/page": "app/dashboard/finance/accounting/page.js",
  "/dashboard/finance/savings/page": "app/dashboard/finance/savings/page.js",
  "/dashboard/finance/super/page": "app/dashboard/finance/super/page.js",
  "/dashboard/finance/page": "app/dashboard/finance/page.js",
  "/dashboard/finance/tax/page": "app/dashboard/finance/tax/page.js",
  "/dashboard/formation/[id]/page": "app/dashboard/formation/[id]/page.js",
  "/dashboard/formation/new/page": "app/dashboard/formation/new/page.js",
  "/dashboard/formation/page": "app/dashboard/formation/page.js",
  "/dashboard/grants/page": "app/dashboard/grants/page.js",
  "/dashboard/groups/page": "app/dashboard/groups/page.js",
  "/dashboard/groups/[id]/page": "app/dashboard/groups/[id]/page.js",
  "/dashboard/impact/accessibility/page": "app/dashboard/impact/accessibility/page.js",
  "/dashboard/housing/page": "app/dashboard/housing/page.js",
  "/dashboard/impact/indigenous/page": "app/dashboard/impact/indigenous/page.js",
  "/dashboard/impact/migrant/page": "app/dashboard/impact/migrant/page.js",
  "/dashboard/impact/page": "app/dashboard/impact/page.js",
  "/dashboard/impact/programs/page": "app/dashboard/impact/programs/page.js",
  "/dashboard/impact/reports/page": "app/dashboard/impact/reports/page.js",
  "/dashboard/impact/safety/page": "app/dashboard/impact/safety/page.js",
  "/dashboard/investors/page": "app/dashboard/investors/page.js",
  "/dashboard/jobs/[id]/page": "app/dashboard/jobs/[id]/page.js",
  "/dashboard/learn/applications/page": "app/dashboard/learn/applications/page.js",
  "/dashboard/jobs/page": "app/dashboard/jobs/page.js",
  "/dashboard/learn/[id]/page": "app/dashboard/learn/[id]/page.js",
  "/dashboard/learn/my-courses/page": "app/dashboard/learn/my-courses/page.js",
  "/dashboard/learn/page": "app/dashboard/learn/page.js",
  "/dashboard/learn/providers/[slug]/page": "app/dashboard/learn/providers/[slug]/page.js",
  "/dashboard/mentors/become-mentor/page": "app/dashboard/mentors/become-mentor/page.js",
  "/dashboard/learn/providers/page": "app/dashboard/learn/providers/page.js",
  "/dashboard/mentors/[id]/page": "app/dashboard/mentors/[id]/page.js",
  "/dashboard/mentors/page": "app/dashboard/mentors/page.js",
  "/dashboard/organizations/[slug]/page": "app/dashboard/organizations/[slug]/page.js",
  "/dashboard/notifications/page": "app/dashboard/notifications/page.js",
  "/dashboard/persona/[persona]/page": "app/dashboard/persona/[persona]/page.js",
  "/dashboard/page": "app/dashboard/page.js",
  "/dashboard/persona/page": "app/dashboard/persona/page.js",
  "/dashboard/referrals/page": "app/dashboard/referrals/page.js",
  "/dashboard/profile/[id]/page": "app/dashboard/profile/[id]/page.js",
  "/dashboard/rfps/page": "app/dashboard/rfps/page.js",
  "/dashboard/saved-jobs/page": "app/dashboard/saved-jobs/page.js",
  "/dashboard/search/page": "app/dashboard/search/page.js",
  "/dashboard/settings/appearance/page": "app/dashboard/settings/appearance/page.js",
  "/dashboard/settings/billing/page": "app/dashboard/settings/billing/page.js",
  "/dashboard/settings/help/page": "app/dashboard/settings/help/page.js",
  "/dashboard/settings/language/page": "app/dashboard/settings/language/page.js",
  "/dashboard/settings/notifications/page": "app/dashboard/settings/notifications/page.js",
  "/dashboard/settings/page": "app/dashboard/settings/page.js",
  "/dashboard/settings/security/page": "app/dashboard/settings/security/page.js",
  "/dashboard/settings/profile/page": "app/dashboard/settings/profile/page.js",
  "/dashboard/settings/privacy/page": "app/dashboard/settings/privacy/page.js",
  "/dashboard/vendors/page": "app/dashboard/vendors/page.js",
  "/apprenticeships/page": "app/apprenticeships/page.js",
  "/skills-marketplace/page": "app/skills-marketplace/page.js",
  "/explore/page": "app/explore/page.js",
  "/dashboard/messages/[id]/page": "app/dashboard/messages/[id]/page.js",
  "/dashboard/messages/page": "app/dashboard/messages/page.js"
}